{
  "tasks": [
    {
      "text": "New meeting",
      "day": "5TH FEB 1998",
      "reminder": true,
      "id": 4
    },
    {
      "text": "Newest meeting",
      "day": "5th Nov at 3:40PM",
      "reminder": false,
      "id": 5
    },
    {
      "text": "dasjdhas djas dasndasdnsadnadaskjdn ad snkad asdadnlad  dlasd a",
      "day": "kjasndjas da ad ",
      "reminder": false,
      "id": 7
    },
    {
      "text": "sdaa",
      "day": "sadadasd",
      "reminder": false,
      "id": 8
    }
  ]
}